yaml/__init__.py
yaml/_comments.py
yaml/_parser.py
yaml/_scanner.py
yaml/_source.py
yaml/constructor.py
yaml/dumper.py
yaml/emitter.py
yaml/error.py
yaml/events.py
yaml/loader.py
yaml/nodes.py
yaml/reader.py
yaml/representer.py
yaml/resolver.py
yaml/roundtrip.py
yaml/scanner.py
yaml/serializer.py
yaml/tokens.py
pyyaml_pure-0.1.0.dist-info/METADATA
pyyaml_pure-0.1.0.dist-info/WHEEL
pyyaml_pure-0.1.0.dist-info/licenses/LICENSE
pyyaml_pure-0.1.0.dist-info/RECORD
